.gitignore
.pre-commit-config.yaml
.pylintrc
.readthedocs.yaml
CODE_OF_CONDUCT.md
LICENSE
README.rst
README.rst.license
pyproject.toml
requirements.txt
setup.py
.github/PULL_REQUEST_TEMPLATE/adafruit_circuitpython_pr.md
.github/workflows/build.yml
.github/workflows/failure-help-text.yml
.github/workflows/release.yml
.reuse/dep5
LICENSES/CC-BY-4.0.txt
LICENSES/CC0-1.0.txt
LICENSES/MIT.txt
LICENSES/Unlicense.txt
circuitpython_tzdb.egg-info/PKG-INFO
circuitpython_tzdb.egg-info/SOURCES.txt
circuitpython_tzdb.egg-info/dependency_links.txt
circuitpython_tzdb.egg-info/requires.txt
circuitpython_tzdb.egg-info/top_level.txt
docs/api.rst
docs/api.rst.license
docs/conf.py
docs/examples.rst
docs/examples.rst.license
docs/index.rst
docs/index.rst.license
docs/requirements.txt
docs/_static/favicon.ico
docs/_static/favicon.ico.license
examples/tzdb_simpletest.py
tzdb/__init__.py
tzdb/_timezone.py
tzdb/_zones/UTC.py
tzdb/_zones/__init__.py
tzdb/_zones/Africa/Abidjan.py
tzdb/_zones/Africa/Accra.py
tzdb/_zones/Africa/Addis_Ababa.py
tzdb/_zones/Africa/Algiers.py
tzdb/_zones/Africa/Asmara.py
tzdb/_zones/Africa/Asmera.py
tzdb/_zones/Africa/Bamako.py
tzdb/_zones/Africa/Bangui.py
tzdb/_zones/Africa/Banjul.py
tzdb/_zones/Africa/Bissau.py
tzdb/_zones/Africa/Blantyre.py
tzdb/_zones/Africa/Brazzaville.py
tzdb/_zones/Africa/Bujumbura.py
tzdb/_zones/Africa/Cairo.py
tzdb/_zones/Africa/Casablanca.py
tzdb/_zones/Africa/Ceuta.py
tzdb/_zones/Africa/Conakry.py
tzdb/_zones/Africa/Dakar.py
tzdb/_zones/Africa/Dar_es_Salaam.py
tzdb/_zones/Africa/Djibouti.py
tzdb/_zones/Africa/Douala.py
tzdb/_zones/Africa/El_Aaiun.py
tzdb/_zones/Africa/Freetown.py
tzdb/_zones/Africa/Gaborone.py
tzdb/_zones/Africa/Harare.py
tzdb/_zones/Africa/Johannesburg.py
tzdb/_zones/Africa/Juba.py
tzdb/_zones/Africa/Kampala.py
tzdb/_zones/Africa/Khartoum.py
tzdb/_zones/Africa/Kigali.py
tzdb/_zones/Africa/Kinshasa.py
tzdb/_zones/Africa/Lagos.py
tzdb/_zones/Africa/Libreville.py
tzdb/_zones/Africa/Lome.py
tzdb/_zones/Africa/Luanda.py
tzdb/_zones/Africa/Lubumbashi.py
tzdb/_zones/Africa/Lusaka.py
tzdb/_zones/Africa/Malabo.py
tzdb/_zones/Africa/Maputo.py
tzdb/_zones/Africa/Maseru.py
tzdb/_zones/Africa/Mbabane.py
tzdb/_zones/Africa/Mogadishu.py
