Metadata-Version: 2.1
Name: circuitpython-tzdb
Version: 0.0.4
Summary: IANA timezones for adafruit_datetime
Home-page: https://github.com/evindunn/CircuitPython_tzdb.git
Author: Evin Dunn
Author-email: evindunn14@gmail.com
License: MIT
Keywords: adafruit blinka circuitpython micropython tzdb datetime timezone
Platform: UNKNOWN
Classifier: Development Status :: 3 - Alpha
Classifier: Intended Audience :: Developers
Classifier: Topic :: Software Development :: Libraries
Classifier: Topic :: System :: Hardware
Classifier: License :: OSI Approved :: MIT License
Classifier: Programming Language :: Python :: 3
License-File: LICENSE
